mxlpy/__init__.py
mxlpy/carousel.py
mxlpy/compare.py
mxlpy/distributions.py
mxlpy/fns.py
mxlpy/fuzzy.py
mxlpy/identify.py
mxlpy/label_map.py
mxlpy/linear_label_map.py
mxlpy/mc.py
mxlpy/mca.py
mxlpy/model.py
mxlpy/parallel.py
mxlpy/parameterise.py
mxlpy/paths.py
mxlpy/plot.py
mxlpy/py.typed
mxlpy/report.py
mxlpy/scan.py
mxlpy/simulation.py
mxlpy/simulator.py
mxlpy/types.py
mxlpy/units.py
mxlpy/experimental/__init__.py
mxlpy/experimental/diff.py
mxlpy/fit/__init__.py
mxlpy/fit/abstract.py
mxlpy/fit/losses.py
mxlpy/fit/routines.py
mxlpy/integrators/__init__.py
mxlpy/integrators/abstract.py
mxlpy/integrators/int_assimulo.py
mxlpy/integrators/int_diffrax.py
mxlpy/integrators/int_scipy.py
mxlpy/meta/__init__.py
mxlpy/meta/codegen_latex.py
mxlpy/meta/codegen_model.py
mxlpy/meta/codegen_mxlpy.py
mxlpy/meta/source_tools.py
mxlpy/meta/sympy_tools.py
mxlpy/minimizers/__init__.py
mxlpy/minimizers/_scipy.py
mxlpy/minimizers/abstract.py
mxlpy/nn/__init__.py
mxlpy/nn/_equinox.py
mxlpy/nn/_keras.py
mxlpy/nn/_torch.py
mxlpy/npe/__init__.py
mxlpy/npe/_equinox.py
mxlpy/npe/_keras.py
mxlpy/npe/_torch.py
mxlpy/npe/abstract.py
mxlpy/sbml/__init__.py
mxlpy/sbml/_data.py
mxlpy/sbml/_export.py
mxlpy/sbml/_import.py
mxlpy/sbml/_name_conversion.py
mxlpy/surrogates/__init__.py
mxlpy/surrogates/_equinox.py
mxlpy/surrogates/_keras.py
mxlpy/surrogates/_poly.py
mxlpy/surrogates/_qss.py
mxlpy/surrogates/_torch.py
mxlpy/surrogates/abstract.py
mxlpy/symbolic/__init__.py
mxlpy/symbolic/strikepy.py
mxlpy/symbolic/symbolic_model.py
mxlpy-0.30.0.dist-info/METADATA
mxlpy-0.30.0.dist-info/WHEEL
mxlpy-0.30.0.dist-info/licenses/LICENSE
mxlpy-0.30.0.dist-info/RECORD
