Metadata-Version: 2.4
Name: mxlpy
Version: 0.30.0
Summary: A package to build metabolic models
Author-email: Marvin van Aalst <marvin.vanaalst@gmail.com>
Maintainer-email: Marvin van Aalst <marvin.vanaalst@gmail.com>
License-Expression: MIT
License-File: LICENSE
Keywords: metabolic,modelling,ode
Classifier: Development Status :: 5 - Production/Stable
Classifier: Environment :: Console
Classifier: Intended Audience :: Developers
Classifier: Intended Audience :: Science/Research
Classifier: License :: OSI Approved :: MIT License
Classifier: Operating System :: MacOS
Classifier: Operating System :: Microsoft :: Windows
Classifier: Operating System :: OS Independent
Classifier: Operating System :: POSIX
Classifier: Operating System :: Unix
Classifier: Programming Language :: Python :: 3
Classifier: Programming Language :: Python :: 3.11
Classifier: Programming Language :: Python :: 3.12
Classifier: Programming Language :: Python :: 3.13
Classifier: Topic :: Scientific/Engineering
Classifier: Topic :: Software Development
Requires-Python: <3.14,>=3.12
Requires-Dist: dill>=0.3.9
Requires-Dist: latexify-py>=0.4.4
Requires-Dist: lazy-import>=0.2.2
Requires-Dist: matplotlib>=3.9.2
Requires-Dist: mike>=2.1.3
Requires-Dist: more-itertools>=10.5.0
Requires-Dist: numpy>=2.1.2
Requires-Dist: pandas>=2.2.3
Requires-Dist: parameteriser>=0.1.0
Requires-Dist: pebble>=5.0.7
Requires-Dist: pysbml>=0.3.0
Requires-Dist: python-libsbml>=5.20.4
Requires-Dist: salib>=1.5.1
Requires-Dist: scipy>=1.14.1
Requires-Dist: seaborn>=0.13.2
Requires-Dist: symbtools>=0.4.0
Requires-Dist: sympy>=1.13.1
Requires-Dist: tabulate>=0.9.0
Requires-Dist: toml>=0.10.2
Requires-Dist: tqdm>=4.66.6
Requires-Dist: typing-extensions>=4.12.2
Requires-Dist: wadler-lindig>=0.1.7
Provides-Extra: jax
Requires-Dist: diffrax>=0.7.0; extra == 'jax'
Requires-Dist: equinox>=0.13; extra == 'jax'
Requires-Dist: optax>=0.2.5; extra == 'jax'
Requires-Dist: sympy2jax>=0.0.7; extra == 'jax'
Provides-Extra: keras
Requires-Dist: keras>=3.9.2; extra == 'keras'
Provides-Extra: sr
Requires-Dist: pysr>=1.5.9; extra == 'sr'
Provides-Extra: tensorflow
Requires-Dist: tensorflow>=2.19.0; extra == 'tensorflow'
Provides-Extra: torch
Requires-Dist: torch>=2.5.1; extra == 'torch'
